myeia/__init__.py
myeia/api.py
myeia/version.py
myeia-0.4.8.dist-info/LICENSE
myeia-0.4.8.dist-info/METADATA
myeia-0.4.8.dist-info/WHEEL
myeia-0.4.8.dist-info/top_level.txt
myeia-0.4.8.dist-info/RECORD
