Metadata-Version: 2.1
Name: myeia
Version: 0.4.8
Summary: Python Wrapper for the U.S. Energy Information Administration (EIA) APIv2.
Home-page: https://github.com/philsv/myeia
Author: philsv
Author-email: frphsv@gmail.com
License: MIT
Keywords: eia,eia-api,open-data,python
Platform: UNKNOWN
Classifier: Development Status :: 4 - Beta
Classifier: Intended Audience :: Developers
Classifier: Programming Language :: Python :: 3
Classifier: Programming Language :: Python :: 3.8
Classifier: Programming Language :: Python :: 3.9
Classifier: Programming Language :: Python :: 3.10
Classifier: Programming Language :: Python :: 3.11
Classifier: Operating System :: Microsoft :: Windows
Classifier: Operating System :: Unix
Classifier: Operating System :: MacOS :: MacOS X
Classifier: License :: OSI Approved :: MIT License
Requires-Dist: backoff
Requires-Dist: pandas
Requires-Dist: requests
Requires-Dist: python-dotenv
